#######################################################################################################################################
<poster>Rockcrusher</poster>
<fanart>http://s5.postimg.org/asr1ob5tz/Fan.jpg</fanart>
#######################################################################################################################################
http://york.watchkodi.com/
<dir>
<name>[COLOR red]Blood Suckers[/COLOR]</name>
<link>http://york.watchkodi.com/Playlists/BloodSuckers.xml</link>
<thumbnail>http://s5.postimg.org/pvl6yl2yv/Blood_Suckers.jpg</thumbnail>
</dir>
<dir>
<name>[COLOR red]Collections[/COLOR]</name>
<link>http://york.watchkodi.com/Playlists/Collections.xml</link>
<thumbnail>http://s5.postimg.org/vz2riht8n/Collections.jpg</thumbnail>
</dir>
<dir>
<name>[COLOR red]Current Movies[/COLOR]</name>
<link>http://york.watchkodi.com/Playlists/Current%20Movies.xml</link>
<thumbnail>http://s5.postimg.org/so9clhwzr/Current_Movies.jpg</thumbnail>
</dir>
<dir>
<name>[COLOR red]CyBorg[/COLOR]</name>
<link>http://york.watchkodi.com/Playlists/CyBorg.xml</link>
<thumbnail>http://s5.postimg.org/n2rzek2mf/Cyborg.jpg</thumbnail>
</dir>
<dir>
<name>[COLOR red]Fun Times[/COLOR]</name>
<link>http://york.watchkodi.com/Playlists/Fun%20Times.xml</link>
<thumbnail>http://s5.postimg.org/pvg51gwnb/Fun_Times.jpg</thumbnail>
</dir>
<dir>
<name>[COLOR red]Horror[/COLOR]</name>
<link>http://york.watchkodi.com/Playlists/Horror.xml</link>
<thumbnail>http://s5.postimg.org/ax2s45nwn/Horror.png</thumbnail>
</dir>
<dir>
<name>[COLOR red]Rock Zombies[/COLOR]</name>
<link>http://york.watchkodi.com/Playlists/Rock%20Zombies.xml</link>
<thumbnail>http://s5.postimg.org/6iuasbdc7/Rock_Zombies.jpg</thumbnail>
</dir>
<dir>
<name>[COLOR red]Sci-Fi[/COLOR]</name>
<link>http://york.watchkodi.com/Playlists/Sci-Fi.xml</link>
<thumbnail>http://s5.postimg.org/xj83gw1mv/Sci_Fi.jpg</thumbnail>
</dir>
<dir>
<name>[COLOR red]War[/COLOR]</name>
<link>http://york.watchkodi.com/Playlists/War.xml</link>
<thumbnail>http://s5.postimg.org/nxej0lah3/War.jpg</thumbnail>
</dir>
<dir>
<name>[COLOR red]Wheels[/COLOR]</name>
<link>http://york.watchkodi.com/Playlists/Wheels.xml</link>
<thumbnail>http://s5.postimg.org/p28l5ywxz/Wheels.jpg</thumbnail>
</dir>
<dir>
<name>[COLOR red]Alien[/COLOR]</name>
<link>http://york.watchkodi.com/Playlists/Alien.xml</link>
<thumbnail>http://s5.postimg.org/pqdaujn7r/Extraterrestrial.jpg</thumbnail>
</dir>
<dir>
<name>[COLOR red]Lawmen[/COLOR]</name>
<link>http://york.watchkodi.com/Playlists/Lawmen.xml</link>
<thumbnail>http://s5.postimg.org/ckfvougqv/Lawmen.jpg</thumbnail>
</dir>

<dir>
<name>[COLOR red]Heroes[/COLOR]</name>
<link>http://york.watchkodi.com/Playlists/Heroes.xml</link>
<thumbnail>http://s5.postimg.org/7fr4dv5mv/Heros.jpg</thumbnail>
</dir>

<dir>
<name>[COLOR red]Dark Hero[/COLOR]</name>
<link>http://york.watchkodi.com/Playlists/Dark%20Hero.xml</link>
<thumbnail>http://s5.postimg.org/eas2b98p3/Dark_Heros.jpg</thumbnail>
</dir>

<dir>
<name>[COLOR red]Adventure[/COLOR]</name>
<link>http://york.watchkodi.com/Playlists/Adventure.xml</link>
<thumbnail>http://s5.postimg.org/8b1yv6ypz/Adventure.png</thumbnail>
</dir>

<dir>
<name>[COLOR red]Magic[/COLOR]</name>
<link>http://york.watchkodi.com/Playlists/Magic.xml</link>
<thumbnail>http://s5.postimg.org/tngej0x8n/Magic.jpg</thumbnail>
</dir>

<dir>
<name>[COLOR red]Thank you all and congrats to [COLOR blue]@biggdogglbc[/COLOR]for being follower #2000[/COLOR]</name>
<link>http://york.watchkodi.com/Playlists/Twitter.xml</link>
<thumbnail>http://s5.postimg.org/r5xpllyrr/Twitter_image_2.png</thumbnail>
</dir>
